{
	"_" : "class_level",
	"ambience" : "amb_town_rutile",
	"background_prev_text_color" : 3043922,
	"cloud_color" : {
		"_" : "class_palette_reference",
		"base_index" : 8,
		"texture_index" : 9
	},
	"display_name" : "none",
	"eff_bloom_threshold" : 0.96,
	"eff_chromatic_str" : 0.5,
	"gizmos_array" : [],
	"grass_color" : {
		"_" : "class_palette_reference",
		"base_index" : 1,
		"texture_index" : 5
	},
	"grass_colors" : {
		"_" : "class_palette_array",
		"array" : [
			{
				"__Elephant_Circular_Ref__" : 2
			}
		]
	},
	"grass_density" : 0.12,
	"grass_height" : 130,
	"grass_height_variance" : 50,
	"grass_thickness" : 2,
	"ground_cover_models" : {
		"_" : "class_model_spawn_array",
		"array" : [
			{
				"_" : "class_model_spawn",
				"colors" : {
					"_" : "class_palette_array",
					"array" : [
						{
							"_" : "class_palette_reference"
						},
						{
							"_" : "class_palette_reference",
							"base_index" : 2,
							"texture_index" : 3
						},
						{
							"_" : "class_palette_reference",
							"texture_index" : 3
						}
					]
				},
				"model" : {
					"_" : "class_model_reference",
					"filename" : "tinyrock_01"
				}
			},
			{
				"_" : "class_model_spawn",
				"colors" : {
					"_" : "class_palette_array",
					"array" : [
						{
							"_" : "class_palette_reference"
						},
						{
							"_" : "class_palette_reference",
							"base_index" : 2,
							"texture_index" : 3
						},
						{
							"_" : "class_palette_reference",
							"texture_index" : 3
						}
					]
				},
				"model" : {
					"_" : "class_model_reference",
					"filename" : "tinyrock_02"
				}
			},
			{
				"_" : "class_model_spawn",
				"colors" : {
					"_" : "class_palette_array",
					"array" : [
						{
							"_" : "class_palette_reference",
							"base_index" : 5,
							"texture_index" : 0
						},
						{
							"_" : "class_palette_reference",
							"base_index" : 5
						},
						{
							"_" : "class_palette_reference",
							"base_index" : 5,
							"texture_index" : 3
						},
						{
							"_" : "class_palette_reference",
							"texture_index" : 5
						},
						{
							"_" : "class_palette_reference",
							"texture_index" : 3
						}
					]
				},
				"model" : {
					"_" : "class_model_reference",
					"filename" : "tinybush"
				},
				"weight" : 0.8
			}
		],
		"seed" : 818618976
	},
	"models_array" : [],
	"name" : "canyon_secret_2",
	"objects_array" : [
		{
			"_" : "class_object",
			"name" : "objPlayer",
			"obj_guid" : "bac206998f7f957c413db80ade5523be",
			"object" : "objPlayer",
			"x" : 111,
			"y" : 1917
		},
		{
			"_" : "class_object",
			"has_net" : 0,
			"name" : "objGameplay",
			"obj_guid" : "5a78622cdf84c786216998e189854b5e",
			"object" : "objGameplay",
			"x" : 2885,
			"y" : 991
		},
		{
			"_" : "class_object",
			"name" : "objTrainboss",
			"obj_guid" : "abaabbae1ad99c9267565e3923f80113",
			"object" : "objTrainboss",
			"x" : 2888,
			"y" : 982
		}
	],
	"palette_name" : "cliffs",
	"palette_reference" : {
		"_" : "class_palette_reference",
		"channel_index" : 1,
		"texture_index" : 5
	},
	"shadow_alpha" : 0.35,
	"shadow_color" : 12583424,
	"shape_groups_array" : [
		{
			"_" : "class_shape_group",
			"shapes_array" : [
				{
					"_" : "class_shape",
					"flat" : 1,
					"grass" : 1,
					"grass_model_array" : {
						"_" : "class_model_spawn_array",
						"array" : [
							{
								"_" : "class_model_spawn",
								"colors" : {
									"_" : "class_palette_array",
									"array" : []
								},
								"model" : {
									"_" : "class_model_reference"
								}
							}
						],
						"seed" : 3865945598
					},
					"ground_cover_update_v1" : 1,
					"object" : {
						"_" : "class_object_reference"
					},
					"palette_reference" : {
						"_" : "class_palette_reference"
					},
					"points_array" : [
						-497,
						244,
						0,
						-445,
						776,
						0,
						-301,
						433,
						0,
						-132,
						316,
						0,
						-24,
						99,
						0,
						96,
						-73,
						0,
						253,
						-136,
						0,
						618,
						-189,
						0,
						197,
						-280,
						0,
						-281,
						-54,
						0
					],
					"ramp" : {
						"_" : "class_ramp"
					},
					"side_palette_reference" : {
						"_" : "class_palette_reference",
						"base_index" : 2,
						"texture_index" : 3
					},
					"x" : 892,
					"y" : 30
				}
			],
			"x" : 1166,
			"y" : 747
		},
		{
			"_" : "class_shape_group",
			"shapes_array" : [
				{
					"_" : "class_shape",
					"flat" : 1,
					"grass" : 1,
					"grass_model_array" : {
						"_" : "class_model_spawn_array",
						"array" : [
							{
								"_" : "class_model_spawn",
								"colors" : {
									"_" : "class_palette_array",
									"array" : []
								},
								"model" : {
									"_" : "class_model_reference"
								}
							}
						],
						"seed" : 1196889977
					},
					"ground_cover_update_v1" : 1,
					"object" : {
						"_" : "class_object_reference"
					},
					"palette_reference" : {
						"_" : "class_palette_reference"
					},
					"points_array" : [
						153,
						217,
						0,
						481,
						759,
						0,
						389,
						163,
						0,
						257,
						-587,
						0,
						-569,
						-578,
						0,
						-698,
						-523,
						0,
						-650,
						-451,
						0,
						-397,
						-324,
						0,
						-108,
						-369,
						0,
						24,
						-108,
						0
					],
					"ramp" : {
						"_" : "class_ramp"
					},
					"side_palette_reference" : {
						"_" : "class_palette_reference",
						"base_index" : 2,
						"texture_index" : 3
					},
					"x" : 1229,
					"y" : -629
				}
			],
			"x" : 2550,
			"y" : 1703
		},
		{
			"_" : "class_shape_group",
			"shapes_array" : [
				{
					"_" : "class_shape",
					"flat" : 1,
					"grass" : 1,
					"grass_model_array" : {
						"_" : "class_model_spawn_array",
						"array" : [
							{
								"_" : "class_model_spawn",
								"colors" : {
									"_" : "class_palette_array",
									"array" : []
								},
								"model" : {
									"_" : "class_model_reference"
								}
							}
						],
						"seed" : 1969679197
					},
					"ground_cover_update_v1" : 1,
					"object" : {
						"_" : "class_object_reference"
					},
					"palette_reference" : {
						"_" : "class_palette_reference"
					},
					"points_array" : [
						-1159,
						876,
						0,
						605,
						750,
						0,
						1375,
						108,
						0,
						1312,
						-163,
						0,
						662,
						-91,
						0,
						361,
						-109,
						0,
						-12,
						63,
						0,
						-300,
						289,
						0,
						-641,
						352,
						0,
						-1564,
						469,
						0
					],
					"ramp" : {
						"_" : "class_ramp"
					},
					"side_palette_reference" : {
						"_" : "class_palette_reference",
						"base_index" : 2,
						"texture_index" : 3
					},
					"x" : 892,
					"y" : 30
				}
			],
			"x" : 1960,
			"y" : 1803
		},
		{
			"_" : "class_shape_group",
			"shapes_array" : [
				{
					"_" : "class_shape",
					"flat" : 1,
					"grass_model_array" : {
						"_" : "class_model_spawn_array",
						"array" : [
							{
								"_" : "class_model_spawn",
								"colors" : {
									"_" : "class_palette_array",
									"array" : []
								},
								"model" : {
									"_" : "class_model_reference"
								}
							}
						],
						"seed" : 6801836
					},
					"ground_cover_update_v1" : 1,
					"map_solid" : 1,
					"object" : {
						"_" : "class_object_reference"
					},
					"palette_reference" : {
						"_" : "class_palette_reference",
						"base_index" : 5,
						"channel_index" : 1,
						"texture_index" : 0
					},
					"points_array" : [
						-1725,
						244,
						0,
						-59,
						305,
						0,
						340,
						405,
						0,
						730,
						327,
						0,
						871,
						119,
						0,
						790,
						-276,
						0,
						1018,
						-664,
						0,
						1476,
						-935,
						0,
						1897,
						-836,
						0,
						2354,
						-872,
						0,
						2836,
						-917,
						0,
						3161,
						-718,
						0,
						3329,
						-186,
						0,
						3197,
						518,
						0,
						2812,
						753,
						0,
						2643,
						942,
						0,
						2114,
						1159,
						0,
						1319,
						1240,
						0,
						1046,
						1074,
						0,
						699,
						949,
						0,
						74,
						1054,
						0,
						-1786,
						1049,
						0,
						-3098,
						3260,
						0,
						4785,
						3197,
						0,
						5025,
						-2291,
						0,
						-2375,
						-1937,
						0
					],
					"ramp" : {
						"_" : "class_ramp"
					},
					"side_palette_reference" : {
						"_" : "class_palette_reference",
						"base_index" : 3,
						"texture_index" : 2
					},
					"solid" : 1,
					"z" : 400
				}
			],
			"x" : 774,
			"y" : 1452
		}
	],
	"sky_gradient" : {
		"_" : "class_palette_reference",
		"base_index" : 6,
		"texture_index" : 7
	},
	"sunlight_color" : 11853055,
	"sunlight_direction" : 135,
	"sunlight_elevation" : 40,
	"water_color" : {
		"_" : "class_palette_reference",
		"base_index" : 10,
		"texture_index" : 11
	}
}